dayz_dev_tools_ext.cp312-win32.pyd
dayz_dev_tools/__init__.py
dayz_dev_tools/config_cpp.py
dayz_dev_tools/expand.py
dayz_dev_tools/extract_pbo.py
dayz_dev_tools/guid.py
dayz_dev_tools/keys.py
dayz_dev_tools/launch_settings.py
dayz_dev_tools/list_pbo.py
dayz_dev_tools/logging_configuration.py
dayz_dev_tools/misc.py
dayz_dev_tools/pbo.py
dayz_dev_tools/pbo_file.py
dayz_dev_tools/pbo_file_reader.py
dayz_dev_tools/pbo_reader.py
dayz_dev_tools/pbo_writer.py
dayz_dev_tools/py.typed
dayz_dev_tools/run_server.py
dayz_dev_tools/script_logs.py
dayz_dev_tools/server_config.py
dayz_dev_tools/tools_directory.py
dayz_dev_tools/unpbo.py
dayz_dev_tools-1.8.1.dist-info/LICENSE
dayz_dev_tools-1.8.1.dist-info/METADATA
dayz_dev_tools-1.8.1.dist-info/WHEEL
dayz_dev_tools-1.8.1.dist-info/entry_points.txt
dayz_dev_tools-1.8.1.dist-info/top_level.txt
dayz_dev_tools-1.8.1.dist-info/RECORD
