Metadata-Version: 2.1
Name: dayz-dev-tools
Version: 1.8.1
Summary: Useful tools for DayZ mod developers.
Author-email: Tim Jensen <tim.l.jensen@gmail.com>
License: MIT License
Project-URL: Homepage, https://dayz-dev-tools.readthedocs.io/
Project-URL: Repository, https://github.com/tjensen/dayz-dev-tools
Project-URL: Issues, https://github.com/tjensen/dayz-dev-tools/issues
Project-URL: Changelog, https://github.com/tjensen/dayz-dev-tools/releases
Keywords: dayz,tools,pbo,server
Classifier: Development Status :: 5 - Production/Stable
Classifier: Environment :: Console
Classifier: License :: OSI Approved :: MIT License
Classifier: Programming Language :: Python :: 3.9
Classifier: Programming Language :: Python :: 3.10
Classifier: Programming Language :: Python :: 3.11
Classifier: Programming Language :: Python :: 3.12
Classifier: Programming Language :: Python :: 3.13
Classifier: Topic :: Games/Entertainment :: First Person Shooters
Classifier: Topic :: Software Development :: Build Tools
Classifier: Topic :: Utilities
Classifier: Typing :: Typed
Requires-Python: >=3.9
License-File: LICENSE
Requires-Dist: pydantic>=2.8.2
Requires-Dist: tomli>=2.0.0; python_version < "3.11"
Provides-Extra: dev
Requires-Dist: build==1.2.2.post1; extra == "dev"
Requires-Dist: flake8==7.1.1; extra == "dev"
Requires-Dist: mypy==1.13.0; extra == "dev"
Requires-Dist: pytest==8.3.4; extra == "dev"
Provides-Extra: publish
Requires-Dist: twine==5.1.1; extra == "publish"
Provides-Extra: docs
Requires-Dist: readthedocs-sphinx-search>=0.3.2; extra == "docs"
Requires-Dist: Sphinx>=4.1.2; extra == "docs"
Requires-Dist: sphinx-rtd-theme; extra == "docs"
